MySQLConnectorCXX/MySQLConnectorCXX.cp37-win_amd64.pyd
MySQLConnectorCXX/MySQLConnectorCXX.pyi
MySQLConnectorCXX/__init__.py
MySQLConnectorCXX-1.0.0.dist-info/LICENSE.txt
MySQLConnectorCXX-1.0.0.dist-info/METADATA
MySQLConnectorCXX-1.0.0.dist-info/WHEEL
MySQLConnectorCXX-1.0.0.dist-info/top_level.txt
MySQLConnectorCXX-1.0.0.dist-info/RECORD
